couchbeans/__init__.py
couchbeans/client.py
couchbeans/exceptions.py
couchbeans-0.0.5.dist-info/licenses/LICENSE
couchbeans-0.0.5.dist-info/METADATA
couchbeans-0.0.5.dist-info/WHEEL
couchbeans-0.0.5.dist-info/top_level.txt
couchbeans-0.0.5.dist-info/RECORD
