Metadata-Version: 2.4
Name: couchbeans
Version: 0.0.5
Summary: A CouchDB library for python, focused on network resilience.
Author-email: Alex Baldwin <contact@alexbaldwin.dev>
License: LGPL-3.0
Project-URL: Homepage, https://github.com/habaldwin01/couchbeans
Project-URL: Issues, https://github.com/habaldwin01/couchbeans/issues
Classifier: Programming Language :: Python :: 3
Classifier: Operating System :: OS Independent
Requires-Python: >=3.4
License-File: LICENSE
Requires-Dist: requests>=2.28.0
Dynamic: license-file
